procblockweb/README.MD
procblockweb/__init__.py
procblockweb/requirements.txt
procblockweb/thirdparty.json
procblockweb-0.12.dist-info/LICENSE.rst
procblockweb-0.12.dist-info/METADATA
procblockweb-0.12.dist-info/WHEEL
procblockweb-0.12.dist-info/top_level.txt
procblockweb-0.12.dist-info/RECORD
