Metadata-Version: 2.1
Name: procblockweb
Version: 0.12
Summary: Disables internet access temporarily for a specified executable and executes it with certain arguments.
Home-page: https://github.com/hansalemaos/procblockweb
Author: Johannes Fischer
Author-email: aulasparticularesdealemaosp@gmail.com
License: MIT
Keywords: Disable,internet
Classifier: Development Status :: 4 - Beta
Classifier: Programming Language :: Python :: 3 :: Only
Classifier: Programming Language :: Python :: 3.10
Classifier: Topic :: Software Development :: Libraries :: Python Modules
Classifier: Topic :: Utilities
License-File: LICENSE.rst
Requires-Dist: rlogfi
